README.md
setup.cfg
setup.py
contextional/__init__.py
contextional/__version__.py
contextional/contextional.py
contextional/nose_plugin.py
contextional/pytest_contextional.py
contextional/test.py
contextional/test_it.py
contextional/test_meta_part_a.py
contextional/test_other.py
contextional/test_standard.py
contextional.egg-info/PKG-INFO
contextional.egg-info/SOURCES.txt
contextional.egg-info/dependency_links.txt
contextional.egg-info/entry_points.txt
contextional.egg-info/requires.txt
contextional.egg-info/top_level.txt
contextional/tests/__init__.py
contextional/tests/test_failure.py
contextional/tests/test_success.py
contextional/tests/tools.py