Metadata-Version: 1.1
Name: contextional
Version: 1.6.3
Summary: A functional testing tool for Python
Home-page: https://github.com/SalmonMode/contextional
Author: Chris NeJame
Author-email: cnejame@truveris.com
License: MIT
Download-URL: https://github.com/SalmonMode/contextional/archive/1.6.3.tar.gz
Keywords: testing test-automation functional-testing testing-tools test tests development organization
Platform: UNKNOWN
Classifier: Intended Audience :: Developers
Classifier: Topic :: Software Development :: Code Generators
Classifier: Topic :: Software Development :: Testing
Classifier: Topic :: Software Development :: Quality Assurance
Classifier: License :: OSI Approved :: MIT License
Classifier: Programming Language :: Python :: 2.7
Classifier: Programming Language :: Python :: 3
Classifier: Programming Language :: Python :: 3.0
Classifier: Programming Language :: Python :: 3.1
Classifier: Programming Language :: Python :: 3.2
Classifier: Programming Language :: Python :: 3.3
Classifier: Programming Language :: Python :: 3.4
Classifier: Programming Language :: Python :: 3.5
Classifier: Programming Language :: Python :: 3.6
